brightwebapp/__init__.py
brightwebapp/brightway.py
brightwebapp/modifications.py
brightwebapp/traversal.py
brightwebapp/visualization.py
brightwebapp-1.0.0.dist-info/licenses/LICENSE.txt
brightwebapp-1.0.0.dist-info/METADATA
brightwebapp-1.0.0.dist-info/WHEEL
brightwebapp-1.0.0.dist-info/top_level.txt
brightwebapp-1.0.0.dist-info/RECORD
