Metadata-Version: 2.4
Name: brightwebapp
Version: 1.0.0
Summary: A demonstrator Python package showcasing the integration of the Brightway framework with web applications.
Author-email: Michael Weinold <michaelphilippweinold+brightwebapp@gmail.com>
Maintainer-email: Michael Weinold <michaelphilippweinold+brightwebapp@gmail.com>
License: MIT
Project-URL: source, https://github.com/brightway-lca/brightwebapp
Project-URL: homepage, https://brightwebapp.readthedocs.io
Project-URL: tracker, https://github.com/brightway-lca/brightwebapp/issues
Classifier: Development Status :: 5 - Production/Stable
Classifier: Programming Language :: Python
Classifier: Programming Language :: Python :: 3
Classifier: Programming Language :: Python :: 3.10
Classifier: Programming Language :: Python :: 3.11
Classifier: Programming Language :: Python :: 3.12
Classifier: Natural Language :: English
Classifier: Operating System :: OS Independent
Classifier: Topic :: Scientific/Engineering
Requires-Python: >=3.9
License-File: LICENSE.txt
Requires-Dist: pandas>=1.3.0
Requires-Dist: bw2data==4.5
Requires-Dist: bw2io==0.9.10
Requires-Dist: bw2calc==2.1
Requires-Dist: bw_graph_tools==0.6
Requires-Dist: plotly
Provides-Extra: testing
Requires-Dist: pytest; extra == "testing"
Requires-Dist: pytest-cov; extra == "testing"
Requires-Dist: python-coveralls; extra == "testing"
Provides-Extra: api
Requires-Dist: fastapi; extra == "api"
Requires-Dist: uvicorn[standard]; extra == "api"
Requires-Dist: ecoinvent_interface; extra == "api"
Dynamic: license-file
